LICENSE.md
MANIFEST.in
README.md
pyproject.toml
setup.py
src/cddlib/lib-src/cddcore.c
src/cddlib/lib-src/cddio.c
src/cddlib/lib-src/cddlib.c
src/cddlib/lib-src/cddlp.c
src/cddlib/lib-src/cddmp.c
src/cddlib/lib-src/cddproj.c
src/cddlib/lib-src/setoper.c
src/include/cddlib/cdd.h
src/include/cddlib/cddmp.h
src/include/cddlib/cddtypes.h
src/include/cddlib/setoper.h
src/include/cddlib/splitmix64.h
src/pycddlib/cdd.pyx
src/pycddlib/extern_cddlib.pxi
src/pycddlib/extern_mytype.pxi
src/pycddlib/extern_preamble.pxi
src/cddlib/lib-src/cddcore.c
src/cddlib/lib-src/cddio.c
src/cddlib/lib-src/cddlib.c
src/cddlib/lib-src/cddlp.c
src/cddlib/lib-src/cddmp.c
src/cddlib/lib-src/cddproj.c
src/cddlib/lib-src/setoper.c
src/include/cddlib/cdd.h
src/include/cddlib/cddmp.h
src/include/cddlib/cddtypes.h
src/include/cddlib/setoper.h
src/include/cddlib/splitmix64.h
src/pycddlib/cdd.pyx
src/pycddlib/extern_cddlib.pxi
src/pycddlib/extern_mytype.pxi
src/pycddlib/extern_preamble.pxi
src/pycddlib_standalone.egg-info/PKG-INFO
src/pycddlib_standalone.egg-info/SOURCES.txt
src/pycddlib_standalone.egg-info/dependency_links.txt
src/pycddlib_standalone.egg-info/top_level.txt