Metadata-Version: 2.1
Name: pycddlib-standalone
Version: 3.0.0a0
Summary: Standalone version of pycddlib
Author-email: "Matthias C. M. Troffaes" <matthias.troffaes@gmail.com>
Project-URL: Homepage, https://github.com/mcmtroffaes/pycddlib-standalone
Project-URL: Documentation, https://pycddlib.readthedocs.io/
Project-URL: Repository, https://github.com/mcmtroffaes/pycddlib-standalone.git
Project-URL: Issues, https://github.com/mcmtroffaes/pycddlib-standalone/issues
Project-URL: Changelog, https://github.com/mcmtroffaes/pycddlib-standalone/blob/main/CHANGELOG.md
Keywords: convex, polyhedron, linear programming, double description method
Classifier: Development Status :: 3 - Alpha
Classifier: License :: OSI Approved :: GNU General Public License v2 or later (GPLv2+)
Classifier: Intended Audience :: Science/Research
Classifier: Topic :: Scientific/Engineering :: Mathematics
Classifier: Programming Language :: C
Classifier: Programming Language :: Cython
Classifier: Programming Language :: Python
Classifier: Programming Language :: Python :: 3
Classifier: Operating System :: OS Independent
Requires-Python: >=3.8
License-File: LICENSE.md
